linkhouWebSocketClient.py
AGVlinkhou-1.0.3.dist-info/LICENSE
AGVlinkhou-1.0.3.dist-info/METADATA
AGVlinkhou-1.0.3.dist-info/WHEEL
AGVlinkhou-1.0.3.dist-info/top_level.txt
AGVlinkhou-1.0.3.dist-info/RECORD
