Metadata-Version: 2.1
Name: AGVlinkhou
Version: 1.0.3
Summary: learn
Author-email: Zhang Xu Ri <1371062508@qq.com>
Project-URL: Homepage, https://github.com/Huangri-believe/LinkHouAGV
Classifier: Programming Language :: Python :: 3
Classifier: License :: OSI Approved :: MIT License
Classifier: Operating System :: OS Independent
Requires-Python: >=3.7
License-File: LICENSE
Requires-Dist: schedule~=1.1.0
Requires-Dist: websocket-client~=1.5.1
Requires-Dist: rel~=0.4.8
Requires-Dist: transitions~=0.9.0
Requires-Dist: shapely~=2.0.2
Requires-Dist: ruamel.yaml~=0.18.6
Requires-Dist: requests
